ccc_cuda_ext.cpython-313-x86_64-linux-gnu.so
ccc/__init__.py
ccc/conf.py
ccc/corr.py
ccc/giant.py
ccc/log.py
ccc/log_config.yaml
ccc/methods.py
ccc/plots.py
ccc/pyproject.toml
ccc/settings.py
ccc/coef/__init__.py
ccc/coef/impl.py
ccc/coef/impl_gpu.py
ccc/numpy/__init__.py
ccc/pytorch/__init__.py
ccc/pytorch/core.py
ccc/scipy/__init__.py
ccc/scipy/stats.py
ccc/sklearn/__init__.py
ccc/sklearn/metrics.py
ccc/sklearn/metrics_gpu.py
ccc/utils/__init__.py
ccc/utils/utility_functions.py
include/gmock/internal/custom/README.md
include/gtest/internal/custom/README.md
lib64/libgmock.a
lib64/libgmock_main.a
lib64/libgtest.a
lib64/libgtest_main.a
lib64/cmake/GTest/GTestConfig.cmake
lib64/cmake/GTest/GTestConfigVersion.cmake
lib64/cmake/GTest/GTestTargets-release.cmake
lib64/cmake/GTest/GTestTargets.cmake
lib64/pkgconfig/gmock.pc
lib64/pkgconfig/gmock_main.pc
lib64/pkgconfig/gtest.pc
lib64/pkgconfig/gtest_main.pc
cccgpu-0.2.4.dist-info/METADATA
cccgpu-0.2.4.dist-info/WHEEL
cccgpu-0.2.4.dist-info/RECORD
cccgpu-0.2.4.dist-info/licenses/LICENSE
cccgpu-0.2.4.dist-info/licenses/LICENSE_bundled
