Metadata-Version: 2.2
Name: cccgpu
Version: 0.2.4
Summary: The Clustermatch Correlation Coefficient (CCC) with GPU acceleration
Author-Email: Milton Pividori <milton.pividori@cuanschutz.edu>, Haoyu Zhang <haoyu_z@outlook.com>
License: BSD-2-Clause Plus Patent
Classifier: Programming Language :: Python :: 3
Classifier: License :: OSI Approved :: BSD License
Classifier: Operating System :: OS Independent
Classifier: Development Status :: 5 - Production/Stable
Classifier: Environment :: Console
Requires-Python: >=3.10
Requires-Dist: numpy
Requires-Dist: scipy
Requires-Dist: numba
Requires-Dist: pandas
Requires-Dist: scikit-learn
Provides-Extra: test
Requires-Dist: pytest; extra == "test"
Requires-Dist: pytest-cov; extra == "test"
